more_spark_transformers.py
more_spark_transformers-0.0.3.dist-info/METADATA
more_spark_transformers-0.0.3.dist-info/WHEEL
more_spark_transformers-0.0.3.dist-info/top_level.txt
more_spark_transformers-0.0.3.dist-info/RECORD
