Metadata-Version: 2.1
Name: more-spark-transformers
Version: 0.0.3
Summary: More transformers for Spark ML
Author: Marco Cardoso
License: UNKNOWN
Platform: UNKNOWN
Classifier: Programming Language :: Python :: 3
Classifier: License :: OSI Approved :: MIT License
Classifier: Operating System :: OS Independent
Requires-Python: >=3.6
